Metadata-Version: 1.0
Name: dist-ishan
Version: 0.1
Summary: Gaussian distributions
Home-page: UNKNOWN
Author: Ishan Dubey
Author-email: ishandubey@ishandubey.com
License: UNKNOWN
Platform: UNKNOWN
